skill_ovos_youtube/LICENSE.md
skill_ovos_youtube/MANIFEST.in
skill_ovos_youtube/README.md
skill_ovos_youtube/__init__.py
skill_ovos_youtube/version.py
skill_ovos_youtube/locale/de-de/official.voc
skill_ovos_youtube/locale/de-de/youtube.voc
skill_ovos_youtube/locale/de-de/youtube_skill.voc
skill_ovos_youtube/locale/en-us/official.voc
skill_ovos_youtube/locale/en-us/youtube.voc
skill_ovos_youtube/locale/en-us/youtube_skill.voc
skill_ovos_youtube/locale/es-es/official.voc
skill_ovos_youtube/locale/es-es/youtube.voc
skill_ovos_youtube/locale/es-es/youtube_skill.voc
skill_ovos_youtube/locale/fr-fr/official.voc
skill_ovos_youtube/locale/fr-fr/youtube.voc
skill_ovos_youtube/locale/fr-fr/youtube_skill.voc
skill_ovos_youtube/locale/it-it/official.voc
skill_ovos_youtube/locale/it-it/youtube.voc
skill_ovos_youtube/locale/it-it/youtube_skill.voc
skill_ovos_youtube/locale/pt-pt/official.voc
skill_ovos_youtube/locale/pt-pt/youtube.voc
skill_ovos_youtube/locale/pt-pt/youtube_skill.voc
skill_ovos_youtube/res/ytube.jpg
skill_ovos_youtube/res/desktop/skill.json
skill_ovos_youtube/skill_simple_youtube.egg-info/PKG-INFO
skill_ovos_youtube/skill_simple_youtube.egg-info/SOURCES.txt
skill_ovos_youtube/skill_simple_youtube.egg-info/dependency_links.txt
skill_ovos_youtube/skill_simple_youtube.egg-info/entry_points.txt
skill_ovos_youtube/skill_simple_youtube.egg-info/requires.txt
skill_ovos_youtube/skill_simple_youtube.egg-info/top_level.txt
skill_simple_youtube-0.1.3.dist-info/LICENSE.md
skill_simple_youtube-0.1.3.dist-info/METADATA
skill_simple_youtube-0.1.3.dist-info/WHEEL
skill_simple_youtube-0.1.3.dist-info/entry_points.txt
skill_simple_youtube-0.1.3.dist-info/top_level.txt
skill_simple_youtube-0.1.3.dist-info/RECORD
