Metadata-Version: 2.1
Name: skill-simple-youtube
Version: 0.1.3
Summary: ovos common play youtube skill plugin
Home-page: https://github.com/OpenVoiceOS/skill-ovos-youtube
Author: JarbasAi
Author-email: jarbasai@mailfence.com
License: Apache-2.0
Keywords: ovos skill plugin
Platform: UNKNOWN
Requires-Dist: tutubo>=2.0.2
Requires-Dist: ovos-utils>=0.1.0
Requires-Dist: ovos-workshop>=0.0.16
